<?xml version="1.0"?>
<conference version="1">
  <id>lightning-php-conference</id>
  <title>Lightning PHP Conference</title>
  <start_date>2019-10-04</start_date>
  <end_date>2019-10-04</end_date>
  <location country=""/>
  <summary type="text"> The inaugural [Lightning PHP Conference](https://lightningphp.org "Lightning PHP 2019") - this one day event will be held in Tampa, Florida on Friday, October 4th, 2019. We look forward to an incredible day of learning, networking, and fun as we invite the PHP world to join us as part of our Lightning PHP community!</summary>
  <content type="markdown"> The inaugural [Lightning PHP Conference](https://lightningphp.org "Lightning PHP 2019") - this one day event will be held in Tampa, Florida on Friday, October 4th, 2019. We look forward to an incredible day of learning, networking, and fun as we invite the PHP world to join us as part of our Lightning PHP community!</content>
  <updated>2019-07-10T01:27:54+00:00</updated>
  <logo width="250" height="250">bc42dfb58b052fa4118225fcb142238893f56ff5bfd7784f8742abc0035403cb.png</logo>
</conference>
