<?xml version="1.0" encoding="UTF-8"?>
<release id="7.1.23">
  <release>7.1.23</release>
  <date>11 Oct 2018</date>
  <version>
    <major>7</major>
    <minor>1</minor>
    <release>23</release>
  </version>
  <source>
    <source>
      <filename>php-7.1.23.tar.bz2</filename>
      <name>PHP 7.1.23 (tar.bz2)</name>
      <sha256>2d79aa86d8f0faa760a712a1d7be50b57838a9770c1dff34020876630c2ecc4b</sha256>
      <md5/>
      <date>11 Oct 2018</date>
    </source>
    <source>
      <filename>php-7.1.23.tar.gz</filename>
      <name>PHP 7.1.23 (tar.gz)</name>
      <sha256>b839a4de32e6770d10b87c2495c070d09277fe61008804b2992466f0dcc5f0fa</sha256>
      <md5/>
      <date>11 Oct 2018</date>
    </source>
    <source>
      <filename>php-7.1.23.tar.xz</filename>
      <name>PHP 7.1.23 (tar.xz)</name>
      <sha256>227a3c76133c3dc1cec937989456cbd89ed00e68e7260c651900dbe1f5b798bc</sha256>
      <md5/>
      <date>11 Oct 2018</date>
    </source>
  </source>
  <tags/>
  <announcements>
    <announcement lang="en">


<p>The PHP development team announces the immediate availability of PHP 7.1.23.
This is a bugfix release.</p>


</announcement>
  </announcements>
  <changes/>
</release>
